{
  "kalistratov_aleksei": {
    "fio": "Калистратов Алексей",
    "coaches": [
      "nikulshin_aleksandr_viktrovich"
    ],
    "participation": [
      {
        "name": "Победитель  Ironstar  Kazan 2017",
        "url": "https://iron-star.com/results/ironstar-113-kazan-2017/result/www.triathlon.org/athletes/results/50028/alexey_kalistratov"
      }
    ],
    "badges": [
      "__ иконки соревнований __"
    ]
  },



  "rostiagaev_dmitrii": {
    "fio": "Ростягаев Дмитрий",
    "coaches": [
      "nikulshin_aleksandr_viktrovich"
    ],
    "participation": [
      {
        "name": "Призер Кленово 201",
        "url": "https://b12.results.zone/klenovo-olympic-2017/races/1483/results"
      }
    ]
  },

  "parienko_artem": {
    "fio": "Париенко Артем",
    "coaches": [
      "nikulshin_aleksandr_viktrovich"
    ],
    "participation": [
      {
        "name": "Победитель Ironsart Zavidovo 201",
        "url": "https://iron-star.com/results/ironstar-1-4-zavidovo-2017/result/"
      }
    ]
  },

  "matiukh_ekaterina": {
    "fio": "Матюх Екатерина",
    "coaches": [
      "nikulshin_aleksandr_viktrovich"
    ],
    "participation": [
      {
        "name": "Призерка Первенства Европы до 23 лет",
        "url": "https://www.triathlon.org/athletes/results/73209/ekaterina_matiukh"
      }
    ]
  },


  "briukhankov_andrei": {
    "fio": "Брюханков Андрей",
    "coaches": [
      "nikulshin_aleksandr_viktrovich"
    ],
    "participation": [
      {
        "name": "Победитель Кубков Европы по триатлон",
        "url": "https://www.triathlon.org/athletes/profile/14190/andrey_bryukhankov"
      }
    ]
  },


  "goldovskii_kirill": {
    "fio": "Голдовский Кирилл",
    "coaches": [
      "nikulshin_aleksandr_viktrovich"
    ],
    "participation": [
      {
        "name": "3 место Hawaii Чемпионат Мира в категории (30-34)",
        "url": "http://eu.ironman.com/triathlon/organizations/all-world-athlete/agr/2017-ironman-final-2018-status-.aspx?sex=M&agegroup=30-34&loc=RUS#axzz57aBBbg"
      }
    ]
  }
}
